cubing_algs/__init__.py
cubing_algs/algorithm.py
cubing_algs/commutator_conjugate.py
cubing_algs/constants.py
cubing_algs/cycles.py
cubing_algs/display.py
cubing_algs/effects.py
cubing_algs/ergonomics.py
cubing_algs/exceptions.py
cubing_algs/face_transforms.py
cubing_algs/facelets.py
cubing_algs/impacts.py
cubing_algs/initial_state.py
cubing_algs/integrity.py
cubing_algs/masks.py
cubing_algs/metrics.py
cubing_algs/move.py
cubing_algs/palettes.py
cubing_algs/parenthesis.py
cubing_algs/parsing.py
cubing_algs/patterns.py
cubing_algs/py.typed
cubing_algs/scrambler.py
cubing_algs/structure.py
cubing_algs/vcube.py
cubing_algs/visual_cube.py
cubing_algs/cases/__init__.py
cubing_algs/cases/case.py
cubing_algs/cases/collection.py
cubing_algs/cases/CFOP/AF2L.json
cubing_algs/cases/CFOP/F2L.json
cubing_algs/cases/CFOP/OLL.json
cubing_algs/cases/CFOP/PLL.json
cubing_algs/cases/Ortega/OLL.json
cubing_algs/cases/Ortega/PBL.json
cubing_algs/extensions/rotate_2x2x2.c
cubing_algs/extensions/rotate_2x2x2.cpython-312-x86_64-linux-gnu.so
cubing_algs/extensions/rotate_3x3x3.c
cubing_algs/extensions/rotate_3x3x3.cpython-312-x86_64-linux-gnu.so
cubing_algs/extensions/rotate_dynamic.c
cubing_algs/extensions/rotate_dynamic.cpython-312-x86_64-linux-gnu.so
cubing_algs/tests/__init__.py
cubing_algs/tests/test_algorithm.py
cubing_algs/tests/test_case.py
cubing_algs/tests/test_cases_api.py
cubing_algs/tests/test_collection.py
cubing_algs/tests/test_commutator_conjugate.py
cubing_algs/tests/test_cycles.py
cubing_algs/tests/test_display.py
cubing_algs/tests/test_effects.py
cubing_algs/tests/test_ergonomics.py
cubing_algs/tests/test_face_transforms.py
cubing_algs/tests/test_facelets.py
cubing_algs/tests/test_impacts.py
cubing_algs/tests/test_initial_state.py
cubing_algs/tests/test_masks.py
cubing_algs/tests/test_metrics.py
cubing_algs/tests/test_move.py
cubing_algs/tests/test_move_permutations.py
cubing_algs-1.0.17.dist-info/METADATA
cubing_algs-1.0.17.dist-info/WHEEL
cubing_algs-1.0.17.dist-info/top_level.txt
cubing_algs-1.0.17.dist-info/RECORD
cubing_algs-1.0.17.dist-info/licenses/LICENSE
