Metadata-Version: 2.4
Name: cubing-algs
Version: 1.0.17
Summary: Python module providing tools manipulating cubing algorithms.
Author-email: Fantomas42 <fantomas42@gmail.com>
License:                     GNU GENERAL PUBLIC LICENSE
Project-URL: repository, https://github.com/Fantomas42/cubing-algs
Keywords: rubick,cube,speedcubing,solve,algorithm
Classifier: Programming Language :: Python
Requires-Python: >=3.8
License-File: LICENSE
Provides-Extra: dev
Requires-Dist: ruff; extra == "dev"
Requires-Dist: mypy; extra == "dev"
Requires-Dist: pytest; extra == "dev"
Requires-Dist: pytest-cov; extra == "dev"
Requires-Dist: pytest-subtests; extra == "dev"
Requires-Dist: nbval; extra == "dev"
Provides-Extra: notebooks
Requires-Dist: jupyterlab; extra == "notebooks"
Dynamic: license-file
